cli/__init__.py
cli/cli.py
train/__init__.py
train/arguments.py
train/constants.py
train/fsdp.py
train/helper.py
train/lora_helper.py
train/main.py
train/preprocess.py
train/train.py
hulu_evaluate-0.0.3.dist-info/METADATA
hulu_evaluate-0.0.3.dist-info/WHEEL
hulu_evaluate-0.0.3.dist-info/entry_points.txt
hulu_evaluate-0.0.3.dist-info/top_level.txt
hulu_evaluate-0.0.3.dist-info/RECORD
