Metadata-Version: 2.2
Name: hulu-evaluate
Version: 0.0.3
Summary: Client library to train and evaluate models on the HuLu benchmark.
Home-page: https://hulu.nytud.hu/
Author: HUN-REN Research Center for Linguistics
Author-email: varga.kristof@nytud.hun-ren.hu
License: apache-2.0
Keywords: machine-learning models natural-language-processing deep-learning evaluation benchmark
Classifier: Intended Audience :: Developers
Classifier: Intended Audience :: Education
Classifier: Intended Audience :: Science/Research
Classifier: License :: OSI Approved :: Apache Software License
Classifier: Operating System :: OS Independent
Classifier: Programming Language :: Python :: 3
Classifier: Programming Language :: Python :: 3 :: Only
Classifier: Programming Language :: Python :: 3.8
Classifier: Programming Language :: Python :: 3.9
Classifier: Programming Language :: Python :: 3.10
Classifier: Programming Language :: Python :: 3.11
Classifier: Topic :: Scientific/Engineering :: Artificial Intelligence
Requires-Python: >=3.8.0
Requires-Dist: huggingface-hub==0.27.1
Requires-Dist: datasets==3.2.0
Requires-Dist: evaluate==0.4.3
Requires-Dist: packaging==24.1
Requires-Dist: pandas==2.2.2
Requires-Dist: peft==0.14.0
Requires-Dist: pyarrow==19.0.0
Requires-Dist: pydantic==2.8.2
Requires-Dist: requests==2.32.3
Requires-Dist: scikit-learn==1.5.1
Requires-Dist: transformers==4.44.0
Requires-Dist: urllib3==2.2.2
Provides-Extra: dev
Requires-Dist: ruff>=0.5.0; extra == "dev"
Requires-Dist: black; extra == "dev"
Requires-Dist: isort; extra == "dev"
Dynamic: author
Dynamic: author-email
Dynamic: classifier
Dynamic: description
Dynamic: description-content-type
Dynamic: home-page
Dynamic: keywords
Dynamic: license
Dynamic: provides-extra
Dynamic: requires-dist
Dynamic: requires-python
Dynamic: summary
